flask_sqlorm/__init__.py
flask_sqlorm/encrypted.py
flask_sqlorm-0.3.1.dist-info/WHEEL
flask_sqlorm-0.3.1.dist-info/METADATA
flask_sqlorm-0.3.1.dist-info/RECORD
