Metadata-Version: 2.4
Name: flask-sqlorm
Version: 0.3.1
Summary: Flask integration for sqlorm
Author: Maxime Bouroumeau-Fuseau
Author-email: Maxime Bouroumeau-Fuseau <maxime.bouroumeau@gmail.com>
License-Expression: MIT
Requires-Dist: flask~=3.0
Requires-Dist: sqlorm-py~=0.3
Requires-Python: >=3.10
Project-URL: Repository, https://github.com/hyperflask/flask-sqlorm
